olive/__init__.py
olive/metadata.py
olivetest/__init__.py
olivetest/metadata.py
olivetest-0.0.3.dist-info/METADATA
olivetest-0.0.3.dist-info/WHEEL
olivetest-0.0.3.dist-info/top_level.txt
olivetest-0.0.3.dist-info/RECORD
