Metadata-Version: 2.1
Name: olivetest
Version: 0.0.3
Summary: a python wrapper for an AIS Database API
Home-page: UNKNOWN
Author: Elizabeth Golden
Author-email: elizabeth.golden@digitalglobe.com
License: UNKNOWN
Platform: UNKNOWN
Requires-Python: >=3
Requires-Dist: requests
Requires-Dist: python-dotenv
